<?xml version="1.0" encoding="utf-8"?>
<XmlConfiguration xmlns="http://www.nh.com/Config">
  <XmlSection Name="RetailTransactionInfo">
    <XmlParameters>
      <XmlParam Key="ReversalRun" Value="False" />
      <XmlParam Key="ReversalRunResult" Value="False" />
      <XmlParam Key="MCN" Value="0" />
      <XmlParam Key="LastDispensedAMT" Value="" />
      <XmlParam Key="ErrorCode" Value="" />
      <XmlParam Key="ErrorMsg" Value="" />
      <XmlParam Key="ErrorCodeList" Value="" />
      <XmlParam Key="MultiLanErrorMsg" Value="" />
      <XmlParam Key="LastWithdrawalDate" Value="" />
      <XmlParam Key="LastWithdrawalTime" Value="" />
      <XmlParam Key="LastRequestedAmount" Value="" />
      <XmlParam Key="LastSurchargeFlag" Value="" />
      <XmlParam Key="LastTransactionNumber" Value="" />
    </XmlParameters>
  </XmlSection>
</XmlConfiguration>